mpy_cross-1.26.0.post2.data/purelib/mpy_cross/__init__.py
mpy_cross-1.26.0.post2.data/purelib/mpy_cross/__main__.py
mpy_cross-1.26.0.post2.data/purelib/mpy_cross/mpy-cross.exe
mpy_cross-1.26.0.post2.data/purelib/mpy_cross/versions.py
mpy_cross-1.26.0.post2.data/purelib/mpy_cross/archive/v1.11/mpy-cross.exe
mpy_cross-1.26.0.post2.data/purelib/mpy_cross/archive/v1.12/mpy-cross.exe
mpy_cross-1.26.0.post2.data/purelib/mpy_cross/archive/v1.19/mpy-cross.exe
mpy_cross-1.26.0.post2.data/purelib/mpy_cross/archive/v1.20.0/mpy-cross.exe
mpy_cross-1.26.0.post2.data/purelib/mpy_cross/archive/v1.22.0/mpy-cross.exe
mpy_cross-1.26.0.post2.data/purelib/mpy_cross/archive/v1.23.0/mpy-cross.exe
mpy_cross-1.26.0.post2.data/purelib/mpy_cross/archive/v1.9/mpy-cross.exe
mpy_cross-1.26.0.post2.data/purelib/mpy_cross/archive/v1.9.3/mpy-cross.exe
mpy_cross-1.26.0.post2.dist-info/licenses/LICENSE
mpy_cross-1.26.0.post2.dist-info/METADATA
mpy_cross-1.26.0.post2.dist-info/WHEEL
mpy_cross-1.26.0.post2.dist-info/entry_points.txt
mpy_cross-1.26.0.post2.dist-info/top_level.txt
mpy_cross-1.26.0.post2.dist-info/RECORD
