Metadata-Version: 2.4
Name: mpy_cross
Version: 1.26.0.post2
Summary: micropython mpy-cross distribution
Home-page: https://gitlab.com/alelec/mpy_cross
Author: Damien George
Author-email: contact@micropython.org
Maintainer: Andrew Leech
Maintainer-email: andrew@alelec.net
License: MIT
License-File: LICENSE
Dynamic: author
Dynamic: author-email
Dynamic: description
Dynamic: home-page
Dynamic: license
Dynamic: license-file
Dynamic: maintainer
Dynamic: maintainer-email
Dynamic: summary
